Workbook

Sheet Read Me
B2: GET LUCKY GOLF — INVESTOR CASE
B3: Valuation bridge — how a 15% stake bought for R8m gets to the exit vision
B6: WHAT THIS MODEL DOES
B7: This workbook reverse-engineers the headline valuations in the pitch (R53.3m today -> R147m in 2029 -> R807m exit; model shown in $ at FX 18.5).
B8: It shows the subscriber growth, recurring revenue, margin and exit-multiple assumptions that have to hold for those
B9: numbers to be real — so the curve looks earned, not asserted. Every figure you can change is colour-coded.
B11: HOW TO READ THE COLOURS (standard financial-model convention)
B12: BLUE text = an input / assumption you can change. These drive everything else.
B13: BLACK text = a formula. Do not type over these; they recalculate.
B14: GREEN text = a figure pulled from another tab in this workbook.
B15: Yellow shading = a key assumption that is based on histroric average.
B17: THE SEVEN TABS
... B24: 7. Investor's Stake — what 15% bought for R8m is worth at each milestone.

Sheet Assumptions
B2: ASSUMPTIONS
B3: Blue = change me. Yellow = confirm Black = calculated.
B5: DEAL TERMS
B6: Investor equity stake | C6: 0.15 | D6: 15% bought for R8m cash
B7: Investment amount (ZAR) | C7: 8000000 | D7: Cash in from investor
B8: Post-money valuation today ($) | C8: =C7/C6/Assumptions!$C$11 | D8: Implied post-money: R8m / 15% = R53.3m (matches pitch floor)
B9: Subscription price (USD / month) | C9: 10 | D9: $10/mo unlocks the challenge
B10: Hole-in-one prize (USD) | C10: 10000 | D10: insured payout per verified ace
B11: ZAR per USD | C11: 18.5 | D11: FX assumption — confirm rate to use
B13: OPERATING TODAY
B14: Paying subscribers at month 0 | C14: 2000 | D14: Current subscribers
B15: Monthly subscriber growth — Year 1 | C15: 0.105 | D15: Launch marketing & PR effect
B16: Monthly subscriber growth — Year 2 | C16: 0.08 | D16: Tapers as base grows; SA + first intl
B17: Monthly subscriber growth — Year 3 | C17: 0.07 | D17: Global markets open (UK/US/ME/Asia)
B18: Monthly churn rate | C18: 0.04 | D18: % of base lost per month
B19: CAC ($/sub) | C19: 12 | D19: $/sub acquisition target (pitch R225)
B21: ECONOMICS
B22: Gross margin | C22: 0.66 | D22: 66% to Get Lucky
B23: On-course marketing (% of revenue) | C23: 0.1 | D23: 10% on-course marketing
B24: Insured prize risk (% of revenue) | C24: 0.24 | D24: 24% premium for full (100%) cover
B25: Per-round ace probability | C25: 8e-05 | D25: ≈1/12,500 per attempt (amateur odds)
B26: Base operating cost / month today ($) | C26: =350000/Assumptions!$C$11 | D26: Today's monthly opex base (pitch R350k/mo)
B27: Ops scaling vs subscribers (0=flat, 1=linear) | C27: 0.65 | D27: 0.65 ≈ service-inclusive SaaS economies of scale
B28: VALUATION
B29: Valuation multiple — ARR (today) | C29: 0 | D29: Solved below to hit $2.16m floor
B30: Valuation multiple — ARR (2028 target) | C30: 2.744619 | D30: Implied by the published R96.8m base-plan milestone (R96.8m / R35.3m) — not a new assumption
B31: Valuation multiple — ARR (2032 exit) | C31: 6 | D31: Rated as global & profitable
B32: Pitch valuation 2028 ($) | C32: =147000000/Assumptions!$C$11 | D32: Pitch milestone — 3-yr plan (R147m, all revenue streams)
B33: Pitch valuation 2032 ($) | C33: =807000000/Assumptions!$C$11 | D33: Pitch exit vision (R807m, all revenue streams)
B34: SPONSORSHIP & EXIT TRAJECTORY
B35: Sponsorship revenue today ($/yr) | C35: =3000000/Assumptions!$C$11 | D35: Pitch baseline (R3m/yr)
B36: Long-term subscriber growth (Y4–Y7, monthly) | C36: 0.018 | D36: To land 2032 model on $27m exit vision
B37: Rounds per subscriber per month | C37: 4 | D37: On-course attempts at the ace

Sheet Build (Monthly)
B2: 36-MONTH BUILD
B3: Subscriber & recurring-revenue build. Growth rate steps by year (see Assumptions).
B5: Month | C5: 1 | D5: 2 | E5: 3 | F5: 4 | G5: 5 | H5: 6 | I5: 7 | J5: 8 | K5: 9 | L5: 10 | M5: 11 | N5: 12 | O5: 13 | P5: 14 | Q5: 15 | R5: 16 | S5: 17 | T5: 18 | U5: 19 | V5: 20 | W5: 21 | X5: 22 | Y5: 23 | Z5: 24 | AA5: 25 | AB5: 26 | AC5: 27 | AD5: 28 | AE5: 29 | AF5: 30 | AG5: 31 | AH5: 32 | AI5: 33 | AJ5: 34 | AK5: 35 | AL5: 36
B6: Opening subscribers | C6: =Assumptions!$C$14 | D6: =C10 | E6: =D10 | F6: =E10 | G6: =F10 | H6: =G10 | I6: =H10 | J6: =I10 | K6: =J10 | ... AL6: =AK10
B7: Net growth rate (mo) | C7: =Assumptions!$C$15 | D7: =Assumptions!$C$15 | E7: =Assumptions!$C$15 | F7: =Assumptions!$C$15 | G7: =Assumptions!$C$15 | H7: =Assumptions!$C$15 | I7: =Assumptions!$C$15 | J7: =Assumptions!$C$15 | ... N7: =Assumptions!$C$15 | O7: =Assumptions!$C$16 | P7: =Assumptions!$C$16 | Q7: =Assumptions!$C$16 | R7: =Assumptions!$C$16 | S7: =Assumptions!$C$16 | T7: =Assumptions!$C$16 | U7: =Assumptions!$C$16 | V7: =Assumptions!$C$16 | ... Z7: =Assumptions!$C$16 | AA7: =Assumptions!$C$17 | AB7: =Assumptions!$C$17 | AC7: =Assumptions!$C$17 | AD7: =Assumptions!$C$17 | AE7: =Assumptions!$C$17 | AF7: =Assumptions!$C$17 | AG7: =Assumptions!$C$17 | AH7: =Assumptions!$C$17 | ... AL7: =Assumptions!$C$17
B8: Gross adds + retained | C8: =C6*(1+C7) | D8: =D6*(1+D7) | E8: =E6*(1+E7) | F8: =F6*(1+F7) | G8: =G6*(1+G7) | H8: =H6*(1+H7) | I8: =I6*(1+I7) | J8: =J6*(1+J7) | ... AL8: =AL6*(1+AL7)
B9: Churned | C9: =-C6*Assumptions!$C$18 | D9: =-D6*Assumptions!$C$18 | E9: =-E6*Assumptions!$C$18 | F9: =-F6*Assumptions!$C$18 | G9: =-G6*Assumptions!$C$18 | H9: =-H6*Assumptions!$C$18 | I9: =-I6*Assumptions!$C$18 | J9: =-J6*Assumptions!$C$18 | ... AL9: =-AL6*Assumptions!$C$18
B10: Closing subscribers | C10: =C8+C9 | D10: =D8+D9 | E10: =E8+E9 | F10: =F8+F9 | G10: =G8+G9 | H10: =H8+H9 | I10: =I8+I9 | J10: =J8+J9 | ... AL10: =AL8+AL9
B11: MRR ($) | C11: =C10*Assumptions!$C$9 | D11: =D10*Assumptions!$C$9 | E11: =E10*Assumptions!$C$9 | F11: =F10*Assumptions!$C$9 | G11: =G10*Assumptions!$C$9 | H11: =H10*Assumptions!$C$9 | I11: =I10*Assumptions!$C$9 | J11: =J10*Assumptions!$C$9 | ... AL11: =AL10*Assumptions!$C$9
B12: Marketing spend ($) | C12: =C11*Assumptions!$C$23 | D12: =D11*Assumptions!$C$23 | E12: =E11*Assumptions!$C$23 | F12: =F11*Assumptions!$C$23 | G12: =G11*Assumptions!$C$23 | H12: =H11*Assumptions!$C$23 | I12: =I11*Assumptions!$C$23 | J12: =J11*Assumptions!$C$23 | ... AL12: =AL11*Assumptions!$C$23
B13: Prize payouts ($) | C13: =Assumptions!$C$10*(INT(SUM($B$10:C10)*Assumptions!$C$37*Assumptions!$C$25)-INT(SUM($B$10:B10)*Assumptions!$C$37*Assumptions!$C$25)) | D13: =Assumptions!$C$10*(INT(SUM($B$10:D10)*Assumptions!$C$37*Assumptions!$C$25)-INT(SUM($B$10:C10)*Assumptions!$C$37*Assumptions!$C$25)) | E13: =Assumptions!$C$10*(INT(SUM($B$10:E10)*Assumptions!$C$37*Assumptions!$C$25)-INT(SUM($B$10:D10)*Assumptions!$C$37*Assumptions!$C$25)) | F13: =Assumptions!$C$10*(INT(SUM($B$10:F10)*Assumptions!$C$37*Assumptions!$C$25)-INT(SUM($B$10:E10)*Assumptions!$C$37*Assumptions!$C$25)) | G13: =Assumptions!$C$10*(INT(SUM($B$10:G10)*Assumptions!$C$37*Assumptions!$C$25)-INT(SUM($B$10:F10)*Assumptions!$C$37*Assumptions!$C$25)) | H13: =Assumptions!$C$10*(INT(SUM($B$10:H10)*Assumptions!$C$37*Assumptions!$C$25)-INT(SUM($B$10:G10)*Assumptions!$C$37*Assumptions!$C$25)) | I13: =Assumptions!$C$10*(INT(SUM($B$10:I10)*Assumptions!$C$37*Assumptions!$C$25)-INT(SUM($B$10:H10)*Assumptions!$C$37*Assumptions!$C$25)) | J13: =Assumptions!$C$10*(INT(SUM($B$10:J10)*Assumptions!$C$37*Assumptions!$C$25)-INT(SUM($B$10:I10)*Assumptions!$C$37*Assumptions!$C$25)) | ... AL13: =Assumptions!$C$10*(INT(SUM($B$10:AL10)*Assumptions!$C$37*Assumptions!$C$25)-INT(SUM($B$10:AK10)*Assumptions!$C$37*Assumptions!$C$25))
B14: Sponsorship ($) | C14: =Assumptions!$C$35/12*C10/$C$10 | D14: =Assumptions!$C$35/12*D10/$C$10 | E14: =Assumptions!$C$35/12*E10/$C$10 | F14: =Assumptions!$C$35/12*F10/$C$10 | G14: =Assumptions!$C$35/12*G10/$C$10 | H14: =Assumptions!$C$35/12*H10/$C$10 | I14: =Assumptions!$C$35/12*I10/$C$10 | J14: =Assumptions!$C$35/12*J10/$C$10 | ... AL14: =Assumptions!$C$35/12*AL10/$C$10

Sheet Simulator
B2: SIMULATOR CHANNEL
B3: Blue = change me. Yellow = key assumption. Black = calculated.
B5: STATUS
B6: Stream status | C6: LAUNCHING 2027 | E6: Revenue stream 4 of 4. Integration funded by this round (20% of the R8m raise).
B7: Lead target operator | C7: Golfzon | E7: 6,500+ venues, ~60% of the global commercial simulator market (Forbes / Seoulz).
B8: Route to market | C8: Ernie Els — direct relationships | E8: Ernie Els has direct relationships with the target operators and opens the door himself. Access, not a contract.
B9: Operator agreements | C9: Not yet signed | E9: No operator agreement is signed as at August 2026. Simulator revenue depends on concluding one.
B10: UNIT ECONOMICS
B11: Entry price (USD) | C11: 1 | E11: Price per in-sim challenge, charged inside the operator software.
B12: Insured prize (USD) | C12: 1000 | E12: Paid by the insurer on a verified ace. Get Lucky carries no prize risk.
B13: Get Lucky share of entry | C13: 0.46 | E13: Residual after operator and insurer shares. Key commercial assumption — confirm on signature.
B14: Operator share of entry | C14: 0.3 | E14: More than a course 10%: the operator brings venues, software surface and distribution; Get Lucky installs no hardware.
B15: Insurer share of entry | C15: 0.24 | E15: Held identical to the on-course insurance premium assumption.
B16: Check — shares total 100% | C16: =C13+C14+C15 | E16: Must read 100.0%.
B17: EBITDA margin on Get Lucky share | C17: 0.5 | E17: Software-only channel: no cameras, no installation, no course revenue share. After integration engineering, operator marketing support and platform ops.
B19: VOLUME BASIS
B20: Simulator rounds per year — South Korea | C20: 94000000 | E20: Source: GOLF.com — ~94M rounds logged on Golfzon simulators in South Korea in a single year. Korea ONLY: Golfzon venues elsewhere and all other operators are excluded from this model.
B22: ANNUAL RAMP
B23: Metric | C23: 2026 | D23: 2027 | E23: 2028 | F23: 2029 | G23: 2032
B24: Attach rate (% of Korea rounds) | C24: 0 | D24: 0.003 | E24: 0.008 | F24: 0.015 | G24: 0.04 | I24: 2026 is an integration year — no revenue modelled.
B25: Paid challenges | C25: =$C$20*C24 | D25: =$C$20*D24 | E25: =$C$20*E24 | F25: =$C$20*F24 | G25: =$C$20*G24
B26: Gross entry revenue ($) | C26: =C25*$C$11 | D26: =D25*$C$11 | E26: =E25*$C$11 | F26: =F25*$C$11 | G26: =G25*$C$11
B27: Revenue to Get Lucky ($) | C27: =C26*$C$13 | D27: =D26*$C$13 | E27: =E26*$C$13 | F27: =F26*$C$13 | G27: =G26*$C$13 | I27: This row feeds the Valuation tab (2026 = col C, 2029 = col F, 2032 = col G).
B28: EBITDA contribution ($) | C28: =C27*$C$17 | D28: =D27*$C$17 | E28: =E27*$C$17 | F28: =F27*$C$17 | G28: =G27*$C$17
B29: Memo — revenue to Get Lucky (ZAR) | C29: =C27*Assumptions!$C$11 | D29: =D27*Assumptions!$C$11 | E29: =E27*Assumptions!$C$11 | F29: =F27*Assumptions!$C$11 | G29: =G27*Assumptions!$C$11
B31: SENSITIVITY — 2029
B32: Attach rate | C32: Simulator revenue ($) | D32: Total revenue ($) | E32: Valuation ($) | F32: Valuation (ZAR) | G32: Investor multiple
B33: 0 | C33: =$C$20*B33*$C$11*$C$13 | D33: =Valuation!$D$9+C33 | E33: =D33*Assumptions!$C$30 | F33: =E33*Assumptions!$C$11 | G33: =E33/Assumptions!$C$8 | I33: no adoption — model floor
B34: 0.005 | C34: =$C$20*B34*$C$11*$C$13 | D34: =Valuation!$D$9+C34 | E34: =D34*Assumptions!$C$30 | F34: =E34*Assumptions!$C$11 | G34: =E34/Assumptions!$C$8 | I34: conservative
B35: 0.015 | C35: =$C$20*B35*$C$11*$C$13 | D35: =Valuation!$D$9+C35 | E35: =D35*Assumptions!$C$30 | F35: =E35*Assumptions!$C$11 | G35: =E35/Assumptions!$C$8 | I35: the plan
B36: 0.03 | C36: =$C$20*B36*$C$11*$C$13 | D36: =Valuation!$D$9+C36 | E36: =D36*Assumptions!$C$30 | F36: =E36*Assumptions!$C$11 | G36: =E36/Assumptions!$C$8 | I36: strong
B38: Investor multiple = company valuation at the 2029 milestone divided by the post-money valuation of this round. Attach rate is a live input — set it to zero to model the group without the simulator stream.

Sheet Sponsorship
B2: TERRITORY SPONSORSHIP
B3: Blue = change me. Yellow = key assumption. Black = calculated.
B5: THE PROOF POINT
B6: Market | C6: South Africa | E6: Sponsorship is the one line in the plan that was signed rather than forecast.
B7: Partner | C7: Santam (Authorised FSP 3416)
B8: Status | C8: CONTRACTED
B9: Deal value (ZAR) | C9: 9000000 | E9: R9m over three years, in a market of roughly 150,000 golfers.
B10: Year 1 / 2 / 3 (ZAR) | C10: R2.5m -> R3.0m -> R3.5m
B11: Golfer market | C11: 150000 | E11: The insurer who underwrites the prize is the natural sponsor of it — which is why the deal was signable in a small market and why it repeats in large ones.
B13: South African sponsorship already sits in the "Sponsorship revenue" row of the Valuation tab, off the monthly build. This tab models NEW territories only, so nothing is double-counted.
B15: NEW TERRITORIES
B16: Market | C16: Anchor partner | D16: Entry | E16: 2026 | F16: 2029 | G16: 2032
B17: United States | C17: Anchor insurer partner — appointed at market entry | D17: 2029 | E17: 0 | F17: 2000000 | G17: 4000000 | I17: Live input — set each territory to what you believe.
B18: Europe | C18: Anchor insurer partner — appointed at market entry | D18: 2030 | E18: 0 | F18: 0 | G18: 3000000
B19: Japan | C19: Anchor insurer partner — appointed at market entry | D19: 2031 | E19: 0 | F19: 0 | G19: 2000000
B20: Total new-territory sponsorship (ZAR) | E20: =SUM(E17:E19) | F20: =SUM(F17:F19) | G20: =SUM(G17:G19)
B21: Total new-territory sponsorship ($) | E21: =E20/Assumptions!$C$11 | F21: =F20/Assumptions!$C$11 | G21: =G20/Assumptions!$C$11 | I21: This row feeds the Valuation tab (2026 = col E, 2029 = col F, 2032 = col G).
B22: EBITDA margin on sponsorship | C22: 0.6 | E22: After local activation and partner servicing cost.
B24: Every new-territory figure is set BELOW the South African run-rate at entry, in markets many times its size. Sponsorship is negotiated and lumpy: a linear scale off golfer counts would produce numbers no sponsor would sign. New-territory partners are appointed as each market opens and are not yet in place.

Sheet Upsells
B2: IN-PLAY UPSELLS
B3: Blue = change me. Yellow = key assumption. Black = calculated.
B4: Sold AFTER the entry, when the golfer has already paid and is standing over the ball. Upsells attach to attempts already in the model — they never create new volume, so there is no double-count.
B6: THE MENU
B7: Upsell | C7: Price | D7: Insured | E7: What it does
B8: Jackpot upgrade | C8: $100 | D8: Yes | E8: Trade up mid-round to a shot at a $100,000 insured prize instead of the standard pot.
B9: Double up | C9: $5 | D9: Yes | E9: Doubles the prize if the shot goes in. Cheapest yes on the menu, highest attach.
B10: Three for two | C10: 2x entry | D10: Yes | E10: Three swings for the price of two. More attempts per visit, same prize exposure.
B11: Nearest the pin | C11: $3 | D11: Yes | E11: Guaranteed prize inside three feet — monetises the 12,499 shots in 12,500 that are not an ace.
B12: The highlight reel | C12: $3 | D12: No | E12: The produced clip, scored and branded. No insurance component: pure margin, and every share is marketing.
B13: The group pot | C13: $10 a head | D13: No | E13: A fourball buys in, closest to the pin takes the pot, Get Lucky takes a fee.
B15: ATTACH ASSUMPTIONS
B16: Course & app — attach rate | C16: 0.12 | I16: Share of subscriber rounds that buy at least one upsell. This golfer already pays ~R200 a swing.
B17: Course & app — average spend ($) | C17: 5 | I17: Blend across the menu on an attaching entry.
B18: Simulator — attach rate | C18: 0.05 | I18: Lower: the base simulator entry is $1, so the ask has to be smaller.
B19: Simulator — average spend ($) | C19: 2 | I19: Blend across the menu inside a simulator.
B20: Get Lucky net share | C20: 0.55 | I20: After course or operator share and insurance. Higher than the 46% simulator entry share because part of the menu (highlight reel, group pot) carries no insurance.
B21: EBITDA margin | C21: 0.65 | I21: Sold through the existing checkout: no hardware, no new venue cost.
B22: Rounds per subscriber per month | C22: =Assumptions!$C$37
B24: VOLUME & REVENUE
B25: Metric | E25: 2026 | F25: 2029 | G25: 2032
B26: Subscriber rounds (attempts/yr) | E26: =Valuation!C6*$C$22*12 | F26: =Valuation!D6*$C$22*12 | G26: =Valuation!E6*$C$22*12
B27: Simulator challenges | E27: =Simulator!C25 | F27: =Simulator!F25 | G27: =Simulator!G25
B28: Gross upsell revenue ($) | E28: =0 | F28: =F26*$C$16*$C$17+F27*$C$18*$C$19 | G28: =G26*$C$16*$C$17+G27*$C$18*$C$19 | I28: The menu ships with the app build in 2027, so 2026 is set to zero.
B29: Revenue to Get Lucky ($) | E29: =E28*$C$20 | F29: =F28*$C$20 | G29: =G28*$C$20 | I29: This row feeds the Valuation tab (2026 = col E, 2029 = col F, 2032 = col G).
B30: Memo — revenue to Get Lucky (ZAR) | E30: =E29*Assumptions!$C$11 | F30: =F29*Assumptions!$C$11 | G30: =G29*Assumptions!$C$11

Sheet Valuation
B2: VALUATION BRIDGE
B3: Annual roll-up of the monthly build, then the valuation walk to the pitch milestones.
B5: Metric | C5: 2026 | D5: 2029 (Yr3 plan) | E5: 2032 (Exit vision)
B6: Subscribers/ Entries | C6: ='Build (Monthly)'!C10 | D6: ='Build (Monthly)'!AL10 | E6: ='Build (Monthly)'!AL10*(1+Assumptions!$C$36)^48 | G6: 2032 extends the Yr3 exit ramp
B7: Subscription ARR ($) | C7: =SUM('Build (Monthly)'!C11:N11) | D7: ='Build (Monthly)'!AL11*12 | E7: =E6*Assumptions!$C$9*12 | G7: Sum of MRR across months 1-12 (actual 2026 revenue)
B8: Sponsorship revenue — South Africa ($) | C8: =SUM('Build (Monthly)'!C14:N14) | D8: ='Build (Monthly)'!AL14*12 | E8: =Assumptions!$C$35*E6/$C$6 | G8: The contracted Santam deal, off the monthly build
B9: Courses & app subscription ($) | C9: =C7+C8 | D9: =D7+D8 | E9: =E7+E8 | G9: Installed courses, membership and the global app subscription, plus contracted South African sponsorship
B10: Simulator revenue ($) | C10: =Simulator!C27 | D10: =Simulator!F27 | E10: =Simulator!G27 | G10: From the Simulator tab. Revenue stream 4, live from 2027; integration funded by this round.
B11: Territory sponsorship ($) | C11: =Sponsorship!E21 | D11: =Sponsorship!F21 | E11: =Sponsorship!G21 | G11: From the Sponsorship tab. The signed Santam deal repeated with an anchor insurer partner per new market.
B12: In-play upsells ($) | C12: =Upsells!E29 | D12: =Upsells!F29 | E12: =Upsells!G29 | G12: From the Upsells tab. Attaches to attempts already counted above — never new volume.
B13: Total annual revenue ($) | C13: =C9+C10+C11+C12 | D13: =D9+D10+D11+D12 | E13: =E9+E10+E11+E12 | G13: Drives the valuation walk below.
B14: Gross profit — courses & app ($) | C14: =C9*Assumptions!$C$22 | D14: =D9*Assumptions!$C$22 | E14: =E9*Assumptions!$C$22
B15: EBITDA proxy — courses & app ($) | C15: =C14-Assumptions!$C$26*12*(C6/$C$6)^Assumptions!$C$27-C9*Assumptions!$C$24 | D15: =D14-Assumptions!$C$26*12*(D6/$C$6)^Assumptions!$C$27-D9*Assumptions!$C$24 | E15: =E14-Assumptions!$C$26*12*(E6/$C$6)^Assumptions!$C$27-E9*Assumptions!$C$24 | G15: GP less scaled opex less insurance premium. Prize payouts excluded — carried by the insurer.
B16: EBITDA proxy — simulators ($) | C16: =C10*Simulator!$C$17 | D16: =D10*Simulator!$C$17 | E16: =E10*Simulator!$C$17
B17: EBITDA proxy — territory sponsorship ($) | C17: =C11*Sponsorship!$C$22 | D17: =D11*Sponsorship!$C$22 | E17: =E11*Sponsorship!$C$22
B18: EBITDA proxy — in-play upsells ($) | C18: =C12*Upsells!$C$21 | D18: =D12*Upsells!$C$21 | E18: =E12*Upsells!$C$21
B19: EBITDA proxy — total ($) | C19: =C15+C16+C17+C18 | D19: =D15+D16+D17+D18 | E19: =E15+E16+E17+E18
B20: EBITDA margin (% of total revenue) | C20: =IFERROR(C19/C13,0) | D20: =IFERROR(D19/D13,0) | E20: =IFERROR(E19/E13,0)
B22: VALUATION WALK
B23: Implied revenue multiple | C23: =Assumptions!$C$8/C13 | D23: =Assumptions!$C$30 | E23: =Assumptions!$C$31 | G23: Today solved to the post-money floor; out-years from Assumptions.
B24: Valuation milestone — pitch ($) | C24: =Assumptions!$C$8 | D24: =Assumptions!$C$32 | E24: =Assumptions!$C$33 | G24: Headline figures from the pitch: R53.3m / R147m / R807m.
B25: Valuation — model-implied ($) | C25: =C13*C23 | D25: =D13*D23 | E25: =E13*E23 | G25: Sanity check: does the ramp x multiple reach the milestone?
B27: Memo — model valuation in ZAR | C27: =C25*Assumptions!$C$11 | D27: =D25*Assumptions!$C$11 | E27: =E25*Assumptions!$C$11
B28: Memo — pitch milestone in ZAR | C28: =C24*Assumptions!$C$11 | D28: =D24*Assumptions!$C$11 | E28: =E24*Assumptions!$C$11
B29: Memo — revenue by stream in ZAR | C29: =C13*Assumptions!$C$11 | D29: =D13*Assumptions!$C$11 | E29: =E13*Assumptions!$C$11 | G29: Total revenue in rand. Stream split is rows 9-12 above.
B31: WHY 6x REVENUE AT EXIT (2032)
B32: Engaged subscriber database | C32: Recurring golfers opted into a high-intent niche product are the core asset — a clean, targetable distribution channel for golf brands, media partners and sponsors. The valuation reflects the database itself, not just the topline.
B33: Four rungs plus an upsell menu | C33: Installed courses, membership, the global app subscription and simulators sell the same insured challenge through four channels, with sponsorship attached to each territory. Diversified revenue on one cost base.
B34: Strategic partner optionality | C34: At scale the platform unlocks multiple exit paths: license access to a golf brand, co-brand prize pools with a tour or media rights holder, integrate with a sportsbook, or sell outright to a sports-tech acquirer.
B35: Comparable engaged communities | C35: Engaged-community subscription businesses (Strava, Peloton, Whoop) have transacted in the 5-10x revenue range at similar scale. 6x sits mid-band.
B36: Risk to the multiple | C36: If growth stalls the multiple compresses toward pure SaaS (3-4x), landing 2032 at R404-538m rather than R807m.
B37: Risk to the simulator stream | C37: Simulator revenue depends on concluding operator agreements, which are not yet signed as at August 2026. Ernie Els holds direct relationships with the target operators; the integration this round funds is what makes Get Lucky ready to sign. Set the attach rate to zero on the Simulator tab to model the group without the stream.
B38: Risk to territory sponsorship | C38: South African sponsorship is contracted. New-territory anchor partners are appointed as each market opens and are not yet in place. Per-territory figures are live inputs on the Sponsorship tab.
B39: Risk to upsell attach | C39: Attach rates are modelled, not observed — the menu ships in 2027. They are set against the price point of the underlying entry (12% at $5 on course and app, 5% at $2 in simulators) and are live inputs on the Upsells tab.

Sheet Investor's Stake
B2: INVESTOR'S 15%
B3: R8m cash in for 15%. Here's what that stake rides to.
C5: Today | D5: 2029 (3-yr plan) | E5: 2032 (Exit vision)
B6: Company valuation ($) | C6: =Valuation!C24 | D6: =Valuation!D24 | E6: =Valuation!E24 | F6: From Valuation tab (pitch milestones)
B7: Investor stake % | C7: =Assumptions!$C$6 | D7: =Assumptions!$C$6 | E7: =Assumptions!$C$6 | F7: R8m buys 15% of the company
B8: Investor equity value ($) | C8: =C6*C7 | D8: =D6*D7 | E8: =E6*E7 | F8: What the 15% is worth at each milestone
B9: Entry investment — R4m ($) | C9: =Assumptions!$C$7/Assumptions!$C$11 | D9: =Assumptions!$C$7/Assumptions!$C$11 | E9: =Assumptions!$C$7/Assumptions!$C$11 | F9: R8m converted at the FX assumption
B10: Value created vs cash invested ($) | C10: =C8-C$9 | D10: =D8-D$9 | E10: =E8-E$9 | F10: Upside over the R8m invested
B11: Multiple on invested capital (MOIC) | C11: =C8/C$9 | D11: =D8/D$9 | E11: =E8/E$9 | F11: MOIC on entry. CAGR: ~34% to 2029 (3 yrs)
B12: Memo — investor stake in ZAR | C12: =C8*Assumptions!$C$11 | D12: =D8*Assumptions!$C$11 | E12: =E8*Assumptions!$C$11
B13: Figures reflect the company's stated valuation milestones for the R8m / 15% round and the 3-year plan. They illustrate the trajectory a 15% holding bought for R8m moves with — not a guarantee of return. The 2029 and 2032 milestones include the simulator channel, which is modelled but NOT CONTRACTED; the Simulator tab shows the outcome at a 0% attach rate.
