Workbook

Sheet Read Me
B2: GET LUCKY GOLF CLUB — PRO FORMA
B3: The fourball's money game, in an app — "a golf day in your pocket" — with a Santam-underwritten
B4: $100,000 hole-in-one on the slip. 72-month driver model from January 2027, subscribers from zero.
B6: THE STRUCTURE, AND WHY
B7: 1 · PEER GAMES — free forever. No rake, no per-game fee, no custody. The app keeps score and never
B8: touches the pot: private bets are lawful precisely while no third party takes a fee or holds the
B9: stakes (SA statute; US precedent at a 1% commission). Designed from the statute backwards.
B10: 2 · SUBSCRIPTION — $10/month for access to the app. Organizer-pays: creating games needs a
B11: subscription; invited players ride free. Includes no swings; carries no prize risk.
B12: 3 · INSURED JACKPOT — group-pooled entries on the slip, tiers $1→$500 to $100→$100,000, filmed and
B13: verified, prize paid by the insurer. 24% of every entry ceded as premium on the same swing.
B14: 4 · PEER GMV — money staked between players. An engagement KPI. Revenue: zero, permanently.
... B36: simulator operator agreements — all named gating milestones. No approach made to operators, Aug 2026.

Sheet Dashboard
B2: GET LUCKY GOLF — THE MODEL ON ONE PAGE
B3: Every figure is live off Assumptions and the monthly build. Blue cells on the Assumptions tab restate everything.
B5: REVENUE 2029 | D5: EBITDA 2029 | F5: MILESTONE DEC 2029
B6: =Annual!E17 | D6: =Annual!E27 | F6: =Valuation!D10
B8: INVESTOR MULTIPLE 2029 | D8: PEAK DRAWDOWN | F8: SUBSCRIBERS 2032
B9: =Valuation!D16 | D9: =Valuation!C21 | F9: =Annual!H6
B12: REVENUE BY STREAM (ZAR) | C12: Streams net of third-party shares — the rows add. Peer money in play is a KPI, never revenue.
C13: 2027 | D13: 2028 | E13: 2029 | F13: 2030 | G13: 2031 | H13: 2032
B14: Subscriptions | C14: =Annual!C12 | D14: =Annual!D12 | E14: =Annual!E12 | F14: =Annual!F12 | G14: =Annual!G12 | H14: =Annual!H12
B15: Insured jackpot (net) | C15: =Annual!C13 | D15: =Annual!D13 | E15: =Annual!E13 | F15: =Annual!F13 | G15: =Annual!G13 | H15: =Annual!H13
B16: Installed courses | C16: =Annual!C14 | D16: =Annual!D14 | E16: =Annual!E14 | F16: =Annual!F14 | G16: =Annual!G14 | H16: =Annual!H14
B17: Simulators | C17: =Annual!C15 | D17: =Annual!D15 | E17: =Annual!E15 | F17: =Annual!F15 | G17: =Annual!G15 | H17: =Annual!H15
B18: Sponsorship | C18: =Annual!C16 | D18: =Annual!D16 | E18: =Annual!E16 | F18: =Annual!F16 | G18: =Annual!G16 | H18: =Annual!H16
B19: TOTAL | C19: =Annual!C17 | D19: =Annual!D17 | E19: =Annual!E17 | F19: =Annual!F17 | G19: =Annual!G17 | H19: =Annual!H17
B22: PROFITABILITY & CASH (ZAR) | C22: Costs budgeted line by line. The cumulative-cash trough is the peak drawdown — inside the R8m raise.
C23: 2027 | D23: 2028 | E23: 2029 | F23: 2030 | G23: 2031 | H23: 2032
B24: Total cost | C24: =Annual!C25 | D24: =Annual!D25 | E24: =Annual!E25 | F24: =Annual!F25 | G24: =Annual!G25 | H24: =Annual!H25
B25: EBITDA | C25: =Annual!C27 | D25: =Annual!D27 | E25: =Annual!E27 | F25: =Annual!F27 | G25: =Annual!G27 | H25: =Annual!H27
B26: EBITDA margin | C26: =Annual!C28 | D26: =Annual!D28 | E26: =Annual!E28 | F26: =Annual!F28 | G26: =Annual!G28 | H26: =Annual!H28
B27: Free cash flow | C27: =Annual!C31 | D27: =Annual!D31 | E27: =Annual!E31 | F27: =Annual!F31 | G27: =Annual!G31 | H27: =Annual!H31
B28: Cumulative cash | C28: =Annual!C32 | D28: =Annual!D32 | E28: =Annual!E32 | F28: =Annual!F32 | G28: =Annual!G32 | H28: =Annual!H32
B31: VALUATION & THE INVESTOR | E31: Flat 3.0× revenue at every forward milestone, compressing from the 3.69× this round implies.
C32: This round | D32: Dec 2029 | E32: 2032
B33: Valuation milestone | C33: =Valuation!C10 | D33: =Valuation!D10 | E33: =Valuation!E10
B34: Multiple on the R8m ticket | D34: =Valuation!D16 | E34: =Valuation!E16
B35: IRR to Dec 2029 | D35: =Valuation!D17
B37: Use of funds: App 25% · Ops & Team 25% · Market & brand 25% · Simulators 15% · Pilot 10%.
B38: Unrealised marks on a private holding, not realised returns. Peer GMV revenue: zero, permanently.
B88: CHART DATA (calculated — do not edit)
B89: App build | C89: 25
B90: Ops & Team | C90: 25
B91: Market & brand | C91: 25
B92: Simulators | C92: 15
B93: Pilot | C93: 10
B95: This round | C95: =Valuation!C10
B96: Dec 2029 | C96: =Valuation!D10
B97: 2032 | C97: =Valuation!E10

Sheet Assumptions
B2: ASSUMPTIONS
B3: Every input in the book, in blue — change any blue cell and the whole workbook restates. The pitch site and dataroom quote this sheet at these values.
B5: DEAL
B6: ZAR per USD | C6: 18.5 | D6: FX assumption
B7: Raise (ZAR) | C7: 8000000
B8: Equity offered | C8: 0.15 | D8: 15% — the founder's term. Ernie Els holds a founding 5%, non-diluting, for name, likeness & network.
B9: Post-money (ZAR) | C9: =C7/C8 | D9: R53.3m; pre R45.3m
B11: SUBSCRIBERS (ORGANIZERS)
B12: Conversion target at launch | C12: 2000 | D12: Converted from the 60,000 members reached — ramped over 6 months from ZERO
B13: Conversion ramp (months) | C13: 6
B14: Gross monthly growth — Year 1 | C14: 0.13 | D14: Aggressive build — invite loop + paid marketing; founder-set 100k subscribers by 2032
B15: Gross monthly growth — Year 2 | C15: 0.12
B16: Gross monthly growth — Year 3 | C16: 0.11
B17: Gross monthly growth — Year 4+ | C17: 0.109 | D17: Long-term net ~1.8% + churn
B18: Monthly churn | C18: 0.055 | D18: Struck deliberately hard — defended by group lock-in and the season ledger
B19: Subscription (USD / month) | C19: 10 | D19: For ACCESS TO THE APP. No swings included. No prize risk.
B21: THE GAME LAYER
B22: Active players per subscriber | C22: 2.8 | D22: The fourball multiplier (2.2 sceptic / 3.4 bull)
B23: Money rounds per active per month | C23: 1
B24: Players per slip | C24: 4
B25: Average peer pot per slip (USD) | C25: 40 | D25: KPI ONLY — Get Lucky's share of peer money is ZERO, permanently
B27: THE INSURED JACKPOT
B28: Jackpot attach (% of slips) | C28: 0.35 | D28: THE decisive assumption — measured by the 90-day pilot
B29: Average ticket per player (USD) | C29: 10 | D29: Across the $1–$100 ladder
B30: Get Lucky net share of entries | C30: 0.66 | D30: After 24% premium and venue share
B31: Insurance premium (% of entry) | C31: 0.24 | D31: Ceded on the same swing that creates the risk
B32: Submission loss ratio | C32: 0.319 | D32: Santam submission: $17 wavg entry, $4.08 premium, $1.30 claim, 2.51x breakeven
B34: INSTALLED COURSES
B35: Courses installed today | C35: 25 | D35: The 25 flagship jackpot holes
B36: Courses added per year | C36: 25
B37: Entries per course per year | C37: 400
B38: Average entry (ZAR) | C38: 150 | D38: Realised across 10,000 trailing entries
B39: Get Lucky share | C39: 0.66
B41: COSTS
B42: Payment processing (% of gross collections) | C42: 0.03
B43: Verification (USD per INSURED swing) | C43: 0.5 | D43: Peer games verify themselves — zero verification cost
B44: CAC (USD per gross new ORGANIZER) | C44: 24 | D44: CAC per gross new organizer
B45: Brand & retention (% of revenue) | C45: 0.15 | D45: A global consumer build spends hard on brand
B47: VALUATION
B48: Revenue multiple — every forward milestone | C48: 3 | D48: Flat. The round implies 3.77x on 2027, so it compresses.

Sheet Build (Monthly)
B2: 72-MONTH BUILD — Jan 2027 to Dec 2032
B3: The 72-month engine: subscribers from zero (Jan 2027) → actives → money slips → jackpot entries and peer GMV, month by month. Every other sheet reads from here. Milestone is month 36 (Dec 2029).
B5: Month | C5: 1 | D5: 2 | E5: 3 | F5: 4 | G5: 5 | H5: 6 | I5: 7 | J5: 8 | K5: 9 | L5: 10 | M5: 11 | N5: 12 | O5: 13 | P5: 14 | Q5: 15 | R5: 16 | S5: 17 | T5: 18 | U5: 19 | V5: 20 | W5: 21 | X5: 22 | Y5: 23 | Z5: 24 | AA5: 25 | AB5: 26 | AC5: 27 | AD5: 28 | AE5: 29 | AF5: 30 | AG5: 31 | AH5: 32 | AI5: 33 | AJ5: 34 | AK5: 35 | AL5: 36 | AM5: 37 | AN5: 38 | AO5: 39 | AP5: 40 | AQ5: 41 | AR5: 42 | AS5: 43 | AT5: 44 | AU5: 45 | AV5: 46 | AW5: 47 | AX5: 48 | AY5: 49 | AZ5: 50 | BA5: 51 | BB5: 52 | BC5: 53 | BD5: 54 | BE5: 55 | BF5: 56 | BG5: 57 | BH5: 58 | BI5: 59 | BJ5: 60 | BK5: 61 | BL5: 62 | BM5: 63 | BN5: 64 | BO5: 65 | BP5: 66 | BQ5: 67 | BR5: 68 | BS5: 69 | BT5: 70 | BU5: 71 | BV5: 72
B6: Calendar year | C6: 2027 | D6: 2027 | E6: 2027 | F6: 2027 | G6: 2027 | H6: 2027 | I6: 2027 | J6: 2027 | K6: 2027 | L6: 2027 | M6: 2027 | N6: 2027 | O6: 2028 | P6: 2028 | Q6: 2028 | R6: 2028 | S6: 2028 | T6: 2028 | U6: 2028 | V6: 2028 | W6: 2028 | X6: 2028 | Y6: 2028 | Z6: 2028 | AA6: 2029 | AB6: 2029 | AC6: 2029 | AD6: 2029 | AE6: 2029 | AF6: 2029 | AG6: 2029 | AH6: 2029 | AI6: 2029 | AJ6: 2029 | AK6: 2029 | AL6: 2029 | AM6: 2030 | AN6: 2030 | AO6: 2030 | AP6: 2030 | AQ6: 2030 | AR6: 2030 | AS6: 2030 | AT6: 2030 | AU6: 2030 | AV6: 2030 | AW6: 2030 | AX6: 2030 | AY6: 2031 | AZ6: 2031 | BA6: 2031 | BB6: 2031 | BC6: 2031 | BD6: 2031 | BE6: 2031 | BF6: 2031 | BG6: 2031 | BH6: 2031 | BI6: 2031 | BJ6: 2031 | BK6: 2032 | BL6: 2032 | BM6: 2032 | BN6: 2032 | BO6: 2032 | BP6: 2032 | BQ6: 2032 | BR6: 2032 | BS6: 2032 | BT6: 2032 | BU6: 2032 | BV6: 2032
B7: Year index | C7: 1 | D7: 1 | E7: 1 | F7: 1 | G7: 1 | H7: 1 | I7: 1 | J7: 1 | K7: 1 | L7: 1 | M7: 1 | N7: 1 | O7: 2 | P7: 2 | Q7: 2 | R7: 2 | S7: 2 | T7: 2 | U7: 2 | V7: 2 | W7: 2 | X7: 2 | Y7: 2 | Z7: 2 | AA7: 3 | AB7: 3 | AC7: 3 | AD7: 3 | AE7: 3 | AF7: 3 | AG7: 3 | AH7: 3 | AI7: 3 | AJ7: 3 | AK7: 3 | AL7: 3 | AM7: 4 | AN7: 4 | AO7: 4 | AP7: 4 | AQ7: 4 | AR7: 4 | AS7: 4 | AT7: 4 | AU7: 4 | AV7: 4 | AW7: 4 | AX7: 4 | AY7: 5 | AZ7: 5 | BA7: 5 | BB7: 5 | BC7: 5 | BD7: 5 | BE7: 5 | BF7: 5 | BG7: 5 | BH7: 5 | BI7: 5 | BJ7: 5 | BK7: 6 | BL7: 6 | BM7: 6 | BN7: 6 | BO7: 6 | BP7: 6 | BQ7: 6 | BR7: 6 | BS7: 6 | BT7: 6 | BU7: 6 | BV7: 6
B8: Gross growth rate | C8: =Assumptions!$C$14 | D8: =Assumptions!$C$14 | E8: =Assumptions!$C$14 | F8: =Assumptions!$C$14 | G8: =Assumptions!$C$14 | H8: =Assumptions!$C$14 | I8: =Assumptions!$C$14 | J8: =Assumptions!$C$14 | ... N8: =Assumptions!$C$14 | O8: =Assumptions!$C$15 | P8: =Assumptions!$C$15 | Q8: =Assumptions!$C$15 | R8: =Assumptions!$C$15 | S8: =Assumptions!$C$15 | T8: =Assumptions!$C$15 | U8: =Assumptions!$C$15 | V8: =Assumptions!$C$15 | ... Z8: =Assumptions!$C$15 | AA8: =Assumptions!$C$16 | AB8: =Assumptions!$C$16 | AC8: =Assumptions!$C$16 | AD8: =Assumptions!$C$16 | AE8: =Assumptions!$C$16 | AF8: =Assumptions!$C$16 | AG8: =Assumptions!$C$16 | AH8: =Assumptions!$C$16 | ... AL8: =Assumptions!$C$16 | AM8: =Assumptions!$C$17 | AN8: =Assumptions!$C$17 | AO8: =Assumptions!$C$17 | AP8: =Assumptions!$C$17 | AQ8: =Assumptions!$C$17 | AR8: =Assumptions!$C$17 | AS8: =Assumptions!$C$17 | AT8: =Assumptions!$C$17 | ... BV8: =Assumptions!$C$17
B10: SUBSCRIBERS (organizers)
B11: Opening | C11: 0 | D11: =C15 | E11: =D15 | F11: =E15 | G11: =F15 | H11: =G15 | I11: =H15 | J11: =I15 | K11: =J15 | ... BV11: =BU15
B12: Conversion intake (ramp) | C12: =IF(C5<=Assumptions!$C$13,Assumptions!$C$12/Assumptions!$C$13,0) | D12: =IF(D5<=Assumptions!$C$13,Assumptions!$C$12/Assumptions!$C$13,0) | E12: =IF(E5<=Assumptions!$C$13,Assumptions!$C$12/Assumptions!$C$13,0) | F12: =IF(F5<=Assumptions!$C$13,Assumptions!$C$12/Assumptions!$C$13,0) | G12: =IF(G5<=Assumptions!$C$13,Assumptions!$C$12/Assumptions!$C$13,0) | H12: =IF(H5<=Assumptions!$C$13,Assumptions!$C$12/Assumptions!$C$13,0) | I12: =IF(I5<=Assumptions!$C$13,Assumptions!$C$12/Assumptions!$C$13,0) | J12: =IF(J5<=Assumptions!$C$13,Assumptions!$C$12/Assumptions!$C$13,0) | ... BV12: =IF(BV5<=Assumptions!$C$13,Assumptions!$C$12/Assumptions!$C$13,0)
B13: Organic + invite-converted | C13: =C11*C8 | D13: =D11*D8 | E13: =E11*E8 | F13: =F11*F8 | G13: =G11*G8 | H13: =H11*H8 | I13: =I11*I8 | J13: =J11*J8 | ... BV13: =BV11*BV8
B14: Churned | C14: =-C11*Assumptions!$C$18 | D14: =-D11*Assumptions!$C$18 | E14: =-E11*Assumptions!$C$18 | F14: =-F11*Assumptions!$C$18 | G14: =-G11*Assumptions!$C$18 | H14: =-H11*Assumptions!$C$18 | I14: =-I11*Assumptions!$C$18 | J14: =-J11*Assumptions!$C$18 | ... BV14: =-BV11*Assumptions!$C$18
B15: Closing | C15: =C11+C12+C13+C14 | D15: =D11+D12+D13+D14 | E15: =E11+E12+E13+E14 | F15: =F11+F12+F13+F14 | G15: =G11+G12+G13+G14 | H15: =H11+H12+H13+H14 | I15: =I11+I12+I13+I14 | J15: =J11+J12+J13+J14 | ... BV15: =BV11+BV12+BV13+BV14
B16: Average | C16: =AVERAGE(C11,C15) | D16: =AVERAGE(D11,D15) | E16: =AVERAGE(E11,E15) | F16: =AVERAGE(F11,F15) | G16: =AVERAGE(G11,G15) | H16: =AVERAGE(H11,H15) | I16: =AVERAGE(I11,I15) | J16: =AVERAGE(J11,J15) | ... BV16: =AVERAGE(BV11,BV15)
B18: THE GAME LAYER
B19: Active players (avg) | C19: =C16*Assumptions!$C$22 | D19: =D16*Assumptions!$C$22 | E19: =E16*Assumptions!$C$22 | F19: =F16*Assumptions!$C$22 | G19: =G16*Assumptions!$C$22 | H19: =H16*Assumptions!$C$22 | I19: =I16*Assumptions!$C$22 | J19: =J16*Assumptions!$C$22 | ... BV19: =BV16*Assumptions!$C$22
B20: Money slips | C20: =C19*Assumptions!$C$23/Assumptions!$C$24 | D20: =D19*Assumptions!$C$23/Assumptions!$C$24 | E20: =E19*Assumptions!$C$23/Assumptions!$C$24 | F20: =F19*Assumptions!$C$23/Assumptions!$C$24 | G20: =G19*Assumptions!$C$23/Assumptions!$C$24 | H20: =H19*Assumptions!$C$23/Assumptions!$C$24 | I20: =I19*Assumptions!$C$23/Assumptions!$C$24 | J20: =J19*Assumptions!$C$23/Assumptions!$C$24 | ... BV20: =BV19*Assumptions!$C$23/Assumptions!$C$24
B21: Peer GMV ($) — revenue ZERO | C21: =C20*Assumptions!$C$25 | D21: =D20*Assumptions!$C$25 | E21: =E20*Assumptions!$C$25 | F21: =F20*Assumptions!$C$25 | G21: =G20*Assumptions!$C$25 | H21: =H20*Assumptions!$C$25 | I21: =I20*Assumptions!$C$25 | J21: =J20*Assumptions!$C$25 | ... BV21: =BV20*Assumptions!$C$25
B23: REVENUE ($)
B24: Subscriptions | C24: =C16*Assumptions!$C$19 | D24: =D16*Assumptions!$C$19 | E24: =E16*Assumptions!$C$19 | F24: =F16*Assumptions!$C$19 | G24: =G16*Assumptions!$C$19 | H24: =H16*Assumptions!$C$19 | I24: =I16*Assumptions!$C$19 | J24: =J16*Assumptions!$C$19 | ... BV24: =BV16*Assumptions!$C$19
B25: Jackpot entries — gross | C25: =C20*Assumptions!$C$28*Assumptions!$C$24*Assumptions!$C$29 | D25: =D20*Assumptions!$C$28*Assumptions!$C$24*Assumptions!$C$29 | E25: =E20*Assumptions!$C$28*Assumptions!$C$24*Assumptions!$C$29 | F25: =F20*Assumptions!$C$28*Assumptions!$C$24*Assumptions!$C$29 | G25: =G20*Assumptions!$C$28*Assumptions!$C$24*Assumptions!$C$29 | H25: =H20*Assumptions!$C$28*Assumptions!$C$24*Assumptions!$C$29 | I25: =I20*Assumptions!$C$28*Assumptions!$C$24*Assumptions!$C$29 | J25: =J20*Assumptions!$C$28*Assumptions!$C$24*Assumptions!$C$29 | ... BV25: =BV20*Assumptions!$C$28*Assumptions!$C$24*Assumptions!$C$29
B26: Jackpot — net to Get Lucky | C26: =C25*Assumptions!$C$30 | D26: =D25*Assumptions!$C$30 | E26: =E25*Assumptions!$C$30 | F26: =F25*Assumptions!$C$30 | G26: =G25*Assumptions!$C$30 | H26: =H25*Assumptions!$C$30 | I26: =I25*Assumptions!$C$30 | J26: =J25*Assumptions!$C$30 | ... BV26: =BV25*Assumptions!$C$30
B28: MEMO — INSURANCE
B29: Insured swings | C29: =C20*Assumptions!$C$28*Assumptions!$C$24 | D29: =D20*Assumptions!$C$28*Assumptions!$C$24 | E29: =E20*Assumptions!$C$28*Assumptions!$C$24 | F29: =F20*Assumptions!$C$28*Assumptions!$C$24 | G29: =G20*Assumptions!$C$28*Assumptions!$C$24 | H29: =H20*Assumptions!$C$28*Assumptions!$C$24 | I29: =I20*Assumptions!$C$28*Assumptions!$C$24 | J29: =J20*Assumptions!$C$28*Assumptions!$C$24 | ... BV29: =BV20*Assumptions!$C$28*Assumptions!$C$24
B30: Premium ceded ($) | C30: =C25*Assumptions!$C$31 | D30: =D25*Assumptions!$C$31 | E30: =E25*Assumptions!$C$31 | F30: =F25*Assumptions!$C$31 | G30: =G25*Assumptions!$C$31 | H30: =H25*Assumptions!$C$31 | I30: =I25*Assumptions!$C$31 | J30: =J25*Assumptions!$C$31 | ... BV30: =BV25*Assumptions!$C$31
B31: Expected claims ($) | C31: =C30*Assumptions!$C$32 | D31: =D30*Assumptions!$C$32 | E31: =E30*Assumptions!$C$32 | F31: =F30*Assumptions!$C$32 | G31: =G30*Assumptions!$C$32 | H31: =H30*Assumptions!$C$32 | I31: =I30*Assumptions!$C$32 | J31: =J30*Assumptions!$C$32 | ... BV31: =BV30*Assumptions!$C$32

Sheet Annual
B2: ANNUAL ROLL-UP (ZAR)
B3: Calendar-year totals from the monthly build. Streams are net of third-party shares so the rows add; the memo lines show the insurer's view (gross entries, premium ceded, expected claims).
C5: 2027 | D5: 2028 | E5: 2029 | F5: 2030 | G5: 2031 | H5: 2032
B6: Subscribers (closing) | C6: ='Build (Monthly)'!N15 | D6: ='Build (Monthly)'!Z15 | E6: ='Build (Monthly)'!AL15 | F6: ='Build (Monthly)'!AX15 | G6: ='Build (Monthly)'!BJ15 | H6: ='Build (Monthly)'!BV15
B7: Active players (closing) | C7: =C6*Assumptions!$C$22 | D7: =D6*Assumptions!$C$22 | E7: =E6*Assumptions!$C$22 | F7: =F6*Assumptions!$C$22 | G7: =G6*Assumptions!$C$22 | H7: =H6*Assumptions!$C$22
B8: Money slips | C8: =SUMIF('Build (Monthly)'!$C$6:$BV$6,C$5,'Build (Monthly)'!$C$20:$BV$20) | D8: =SUMIF('Build (Monthly)'!$C$6:$BV$6,D$5,'Build (Monthly)'!$C$20:$BV$20) | E8: =SUMIF('Build (Monthly)'!$C$6:$BV$6,E$5,'Build (Monthly)'!$C$20:$BV$20) | F8: =SUMIF('Build (Monthly)'!$C$6:$BV$6,F$5,'Build (Monthly)'!$C$20:$BV$20) | G8: =SUMIF('Build (Monthly)'!$C$6:$BV$6,G$5,'Build (Monthly)'!$C$20:$BV$20) | H8: =SUMIF('Build (Monthly)'!$C$6:$BV$6,H$5,'Build (Monthly)'!$C$20:$BV$20)
B9: Peer GMV ($) — revenue ZERO | C9: =SUMIF('Build (Monthly)'!$C$6:$BV$6,C$5,'Build (Monthly)'!$C$21:$BV$21) | D9: =SUMIF('Build (Monthly)'!$C$6:$BV$6,D$5,'Build (Monthly)'!$C$21:$BV$21) | E9: =SUMIF('Build (Monthly)'!$C$6:$BV$6,E$5,'Build (Monthly)'!$C$21:$BV$21) | F9: =SUMIF('Build (Monthly)'!$C$6:$BV$6,F$5,'Build (Monthly)'!$C$21:$BV$21) | G9: =SUMIF('Build (Monthly)'!$C$6:$BV$6,G$5,'Build (Monthly)'!$C$21:$BV$21) | H9: =SUMIF('Build (Monthly)'!$C$6:$BV$6,H$5,'Build (Monthly)'!$C$21:$BV$21)
B11: REVENUE
B12: Subscriptions | C12: =SUMIF('Build (Monthly)'!$C$6:$BV$6,C$5,'Build (Monthly)'!$C$24:$BV$24)*Assumptions!$C$6 | D12: =SUMIF('Build (Monthly)'!$C$6:$BV$6,D$5,'Build (Monthly)'!$C$24:$BV$24)*Assumptions!$C$6 | E12: =SUMIF('Build (Monthly)'!$C$6:$BV$6,E$5,'Build (Monthly)'!$C$24:$BV$24)*Assumptions!$C$6 | F12: =SUMIF('Build (Monthly)'!$C$6:$BV$6,F$5,'Build (Monthly)'!$C$24:$BV$24)*Assumptions!$C$6 | G12: =SUMIF('Build (Monthly)'!$C$6:$BV$6,G$5,'Build (Monthly)'!$C$24:$BV$24)*Assumptions!$C$6 | H12: =SUMIF('Build (Monthly)'!$C$6:$BV$6,H$5,'Build (Monthly)'!$C$24:$BV$24)*Assumptions!$C$6
B13: Insured jackpot (net) | C13: =SUMIF('Build (Monthly)'!$C$6:$BV$6,C$5,'Build (Monthly)'!$C$26:$BV$26)*Assumptions!$C$6 | D13: =SUMIF('Build (Monthly)'!$C$6:$BV$6,D$5,'Build (Monthly)'!$C$26:$BV$26)*Assumptions!$C$6 | E13: =SUMIF('Build (Monthly)'!$C$6:$BV$6,E$5,'Build (Monthly)'!$C$26:$BV$26)*Assumptions!$C$6 | F13: =SUMIF('Build (Monthly)'!$C$6:$BV$6,F$5,'Build (Monthly)'!$C$26:$BV$26)*Assumptions!$C$6 | G13: =SUMIF('Build (Monthly)'!$C$6:$BV$6,G$5,'Build (Monthly)'!$C$26:$BV$26)*Assumptions!$C$6 | H13: =SUMIF('Build (Monthly)'!$C$6:$BV$6,H$5,'Build (Monthly)'!$C$26:$BV$26)*Assumptions!$C$6
B14: Installed courses (net 66%) | C14: =37.5*Assumptions!$C$37*Assumptions!$C$38*Assumptions!$C$39 | D14: =62.5*Assumptions!$C$37*Assumptions!$C$38*Assumptions!$C$39 | E14: =87.5*Assumptions!$C$37*Assumptions!$C$38*Assumptions!$C$39 | F14: =112.5*Assumptions!$C$37*Assumptions!$C$38*Assumptions!$C$39 | G14: =137.5*Assumptions!$C$37*Assumptions!$C$38*Assumptions!$C$39 | H14: =162.5*Assumptions!$C$37*Assumptions!$C$38*Assumptions!$C$39
B15: Simulators | C15: 2399820 | D15: 6399520 | E15: 11999100 | F15: 16663000 | G15: 23142000 | H15: 31997600
B16: Sponsorship | C16: 3000000 | D16: 3500000 | E16: 5500000 | F16: 8500000 | G16: 10500000 | H16: 12500000
B17: TOTAL REVENUE | C17: =SUM(C12:C16) | D17: =SUM(D12:D16) | E17: =SUM(E12:E16) | F17: =SUM(F12:F16) | G17: =SUM(G12:G16) | H17: =SUM(H12:H16)
B19: COSTS
B20: Payment processing | C20: =((SUMIF('Build (Monthly)'!$C$6:$BV$6,C$5,'Build (Monthly)'!$C$24:$BV$24)+SUMIF('Build (Monthly)'!$C$6:$BV$6,C$5,'Build (Monthly)'!$C$25:$BV$25))*Assumptions!$C$6+37.5*Assumptions!$C$37*Assumptions!$C$38)*Assumptions!$C$42 | D20: =((SUMIF('Build (Monthly)'!$C$6:$BV$6,D$5,'Build (Monthly)'!$C$24:$BV$24)+SUMIF('Build (Monthly)'!$C$6:$BV$6,D$5,'Build (Monthly)'!$C$25:$BV$25))*Assumptions!$C$6+62.5*Assumptions!$C$37*Assumptions!$C$38)*Assumptions!$C$42 | E20: =((SUMIF('Build (Monthly)'!$C$6:$BV$6,E$5,'Build (Monthly)'!$C$24:$BV$24)+SUMIF('Build (Monthly)'!$C$6:$BV$6,E$5,'Build (Monthly)'!$C$25:$BV$25))*Assumptions!$C$6+87.5*Assumptions!$C$37*Assumptions!$C$38)*Assumptions!$C$42 | F20: =((SUMIF('Build (Monthly)'!$C$6:$BV$6,F$5,'Build (Monthly)'!$C$24:$BV$24)+SUMIF('Build (Monthly)'!$C$6:$BV$6,F$5,'Build (Monthly)'!$C$25:$BV$25))*Assumptions!$C$6+112.5*Assumptions!$C$37*Assumptions!$C$38)*Assumptions!$C$42 | G20: =((SUMIF('Build (Monthly)'!$C$6:$BV$6,G$5,'Build (Monthly)'!$C$24:$BV$24)+SUMIF('Build (Monthly)'!$C$6:$BV$6,G$5,'Build (Monthly)'!$C$25:$BV$25))*Assumptions!$C$6+137.5*Assumptions!$C$37*Assumptions!$C$38)*Assumptions!$C$42 | H20: =((SUMIF('Build (Monthly)'!$C$6:$BV$6,H$5,'Build (Monthly)'!$C$24:$BV$24)+SUMIF('Build (Monthly)'!$C$6:$BV$6,H$5,'Build (Monthly)'!$C$25:$BV$25))*Assumptions!$C$6+162.5*Assumptions!$C$37*Assumptions!$C$38)*Assumptions!$C$42
B21: Verification & claims (insured swings only) | C21: =(SUMIF('Build (Monthly)'!$C$6:$BV$6,C$5,'Build (Monthly)'!$C$29:$BV$29)+37.5*Assumptions!$C$37)*Assumptions!$C$43*Assumptions!$C$6 | D21: =(SUMIF('Build (Monthly)'!$C$6:$BV$6,D$5,'Build (Monthly)'!$C$29:$BV$29)+62.5*Assumptions!$C$37)*Assumptions!$C$43*Assumptions!$C$6 | E21: =(SUMIF('Build (Monthly)'!$C$6:$BV$6,E$5,'Build (Monthly)'!$C$29:$BV$29)+87.5*Assumptions!$C$37)*Assumptions!$C$43*Assumptions!$C$6 | F21: =(SUMIF('Build (Monthly)'!$C$6:$BV$6,F$5,'Build (Monthly)'!$C$29:$BV$29)+112.5*Assumptions!$C$37)*Assumptions!$C$43*Assumptions!$C$6 | G21: =(SUMIF('Build (Monthly)'!$C$6:$BV$6,G$5,'Build (Monthly)'!$C$29:$BV$29)+137.5*Assumptions!$C$37)*Assumptions!$C$43*Assumptions!$C$6 | H21: =(SUMIF('Build (Monthly)'!$C$6:$BV$6,H$5,'Build (Monthly)'!$C$29:$BV$29)+162.5*Assumptions!$C$37)*Assumptions!$C$43*Assumptions!$C$6
B22: Acquisition (organizers) | C22: =SUMIF('Build (Monthly)'!$C$6:$BV$6,C$5,'Build (Monthly)'!$C$13:$BV$13)*Assumptions!$C$44*Assumptions!$C$6+SUMIF('Build (Monthly)'!$C$6:$BV$6,C$5,'Build (Monthly)'!$C$12:$BV$12)*Assumptions!$C$44*Assumptions!$C$6 | D22: =SUMIF('Build (Monthly)'!$C$6:$BV$6,D$5,'Build (Monthly)'!$C$13:$BV$13)*Assumptions!$C$44*Assumptions!$C$6+SUMIF('Build (Monthly)'!$C$6:$BV$6,D$5,'Build (Monthly)'!$C$12:$BV$12)*Assumptions!$C$44*Assumptions!$C$6 | E22: =SUMIF('Build (Monthly)'!$C$6:$BV$6,E$5,'Build (Monthly)'!$C$13:$BV$13)*Assumptions!$C$44*Assumptions!$C$6+SUMIF('Build (Monthly)'!$C$6:$BV$6,E$5,'Build (Monthly)'!$C$12:$BV$12)*Assumptions!$C$44*Assumptions!$C$6 | F22: =SUMIF('Build (Monthly)'!$C$6:$BV$6,F$5,'Build (Monthly)'!$C$13:$BV$13)*Assumptions!$C$44*Assumptions!$C$6+SUMIF('Build (Monthly)'!$C$6:$BV$6,F$5,'Build (Monthly)'!$C$12:$BV$12)*Assumptions!$C$44*Assumptions!$C$6 | G22: =SUMIF('Build (Monthly)'!$C$6:$BV$6,G$5,'Build (Monthly)'!$C$13:$BV$13)*Assumptions!$C$44*Assumptions!$C$6+SUMIF('Build (Monthly)'!$C$6:$BV$6,G$5,'Build (Monthly)'!$C$12:$BV$12)*Assumptions!$C$44*Assumptions!$C$6 | H22: =SUMIF('Build (Monthly)'!$C$6:$BV$6,H$5,'Build (Monthly)'!$C$13:$BV$13)*Assumptions!$C$44*Assumptions!$C$6+SUMIF('Build (Monthly)'!$C$6:$BV$6,H$5,'Build (Monthly)'!$C$12:$BV$12)*Assumptions!$C$44*Assumptions!$C$6
B23: Brand & retention | C23: =C17*Assumptions!$C$45 | D23: =D17*Assumptions!$C$45 | E23: =E17*Assumptions!$C$45 | F23: =F17*Assumptions!$C$45 | G23: =G17*Assumptions!$C$45 | H23: =H17*Assumptions!$C$45
B24: Central budget | C24: 11000000 | D24: 18000000 | E24: 28000000 | F24: 42000000 | G24: 62000000 | H24: 88000000
B25: TOTAL COST | C25: =SUM(C20:C24) | D25: =SUM(D20:D24) | E25: =SUM(E20:E24) | F25: =SUM(F20:F24) | G25: =SUM(G20:G24) | H25: =SUM(H20:H24)
B27: EBITDA | C27: =C17-C25 | D27: =D17-D25 | E27: =E17-E25 | F27: =F17-F25 | G27: =G17-G25 | H27: =H17-H25
B28: EBITDA margin | C28: =C27/C17 | D28: =D27/D17 | E28: =E27/E17 | F28: =F27/F17 | G28: =G27/G17 | H28: =H27/H17
B30: Capex | C30: 4400000 | D30: 3200000 | E30: 2500000 | F30: 2500000 | G30: 2500000 | H30: 2500000
B31: Free cash flow | C31: =C27-C30 | D31: =D27-D30 | E31: =E27-E30 | F31: =F27-F30 | G31: =G27-G30 | H31: =H27-H30
B32: Cumulative cash | C32: =C31 | D32: =C32+D31 | E32: =D32+E31 | F32: =E32+F31 | G32: =F32+G31 | H32: =G32+H31
B34: MEMO — INSURANCE
B35: Jackpot gross entries | C35: =SUMIF('Build (Monthly)'!$C$6:$BV$6,C$5,'Build (Monthly)'!$C$25:$BV$25)*Assumptions!$C$6 | D35: =SUMIF('Build (Monthly)'!$C$6:$BV$6,D$5,'Build (Monthly)'!$C$25:$BV$25)*Assumptions!$C$6 | E35: =SUMIF('Build (Monthly)'!$C$6:$BV$6,E$5,'Build (Monthly)'!$C$25:$BV$25)*Assumptions!$C$6 | F35: =SUMIF('Build (Monthly)'!$C$6:$BV$6,F$5,'Build (Monthly)'!$C$25:$BV$25)*Assumptions!$C$6 | G35: =SUMIF('Build (Monthly)'!$C$6:$BV$6,G$5,'Build (Monthly)'!$C$25:$BV$25)*Assumptions!$C$6 | H35: =SUMIF('Build (Monthly)'!$C$6:$BV$6,H$5,'Build (Monthly)'!$C$25:$BV$25)*Assumptions!$C$6
B36: Premium ceded | C36: =SUMIF('Build (Monthly)'!$C$6:$BV$6,C$5,'Build (Monthly)'!$C$30:$BV$30)*Assumptions!$C$6 | D36: =SUMIF('Build (Monthly)'!$C$6:$BV$6,D$5,'Build (Monthly)'!$C$30:$BV$30)*Assumptions!$C$6 | E36: =SUMIF('Build (Monthly)'!$C$6:$BV$6,E$5,'Build (Monthly)'!$C$30:$BV$30)*Assumptions!$C$6 | F36: =SUMIF('Build (Monthly)'!$C$6:$BV$6,F$5,'Build (Monthly)'!$C$30:$BV$30)*Assumptions!$C$6 | G36: =SUMIF('Build (Monthly)'!$C$6:$BV$6,G$5,'Build (Monthly)'!$C$30:$BV$30)*Assumptions!$C$6 | H36: =SUMIF('Build (Monthly)'!$C$6:$BV$6,H$5,'Build (Monthly)'!$C$30:$BV$30)*Assumptions!$C$6
B37: Expected claims | C37: =SUMIF('Build (Monthly)'!$C$6:$BV$6,C$5,'Build (Monthly)'!$C$31:$BV$31)*Assumptions!$C$6 | D37: =SUMIF('Build (Monthly)'!$C$6:$BV$6,D$5,'Build (Monthly)'!$C$31:$BV$31)*Assumptions!$C$6 | E37: =SUMIF('Build (Monthly)'!$C$6:$BV$6,E$5,'Build (Monthly)'!$C$31:$BV$31)*Assumptions!$C$6 | F37: =SUMIF('Build (Monthly)'!$C$6:$BV$6,F$5,'Build (Monthly)'!$C$31:$BV$31)*Assumptions!$C$6 | G37: =SUMIF('Build (Monthly)'!$C$6:$BV$6,G$5,'Build (Monthly)'!$C$31:$BV$31)*Assumptions!$C$6 | H37: =SUMIF('Build (Monthly)'!$C$6:$BV$6,H$5,'Build (Monthly)'!$C$31:$BV$31)*Assumptions!$C$6
B38: Loss ratio | C38: =C37/C36 | D38: =D37/D36 | E38: =E37/E36 | F38: =F37/F36 | G38: =G37/G36 | H38: =H37/H36

Sheet Insurance
B2: INSURANCE — THE SANTAM SUBMISSION, UNCHANGED
B3: Premium is collected on the same swing that creates the risk. The subscription carries ZERO prize risk.
B5: Premium (% of entry) | C5: 0.24
B6: Cover (% of prize) | C6: 1
B7: Broker commission (% of premium) | C7: 0.2
B8: Per-attempt ace probability | C8: 8e-05
B10: TIER LADDER | D10: Entry → insured prize, with the mix realised across 10,000 trailing entries. $17.00 weighted entry · $4.08 premium · $1.30 expected claim → 31.9% loss ratio, 2.51× breakeven.
B11: Tier | C11: Entry ($) | D11: Prize ($) | E11: Mix | F11: Premium/entry | G11: Exp. claim/entry | H11: Loss ratio
B12: Tier 1 | C12: 1 | D12: 500 | E12: 0.25 | F12: =C12*$C$5 | G12: =D12*$C$8*$C$6 | H12: =G12/F12
B13: Tier 2 | C13: 5 | D13: 2500 | E13: 0.25 | F13: =C13*$C$5 | G13: =D13*$C$8*$C$6 | H13: =G13/F13
B14: Tier 3 | C14: 10 | D14: 10000 | E14: 0.3 | F14: =C14*$C$5 | G14: =D14*$C$8*$C$6 | H14: =G14/F14
B15: Tier 4 | C15: 50 | D15: 50000 | E15: 0.15 | F15: =C15*$C$5 | G15: =D15*$C$8*$C$6 | H15: =G15/F15
B16: Tier 5 | C16: 100 | D16: 100000 | E16: 0.05 | F16: =C16*$C$5 | G16: =D16*$C$8*$C$6 | H16: =G16/F16
B17: Weighted average | C17: =SUMPRODUCT($E$12:$E$16,C12:C16) | D17: =SUMPRODUCT($E$12:$E$16,D12:D16) | E17: =SUM(E12:E16) | F17: =SUMPRODUCT($E$12:$E$16,F12:F16) | G17: =SUMPRODUCT($E$12:$E$16,G12:G16) | H17: =G17/F17
B19: Loss ratio (claims / premium) | C19: =H17
B20: Combined ratio (incl. brokerage) | C20: =(G17+F17*C7)/F17
B21: Breakeven ace frequency multiple | C21: =(F17*(1-C7))/G17
B22: Largest single-event exposure ($) | C22: =MAX(D12:D16)
B24: GROUP-POOLED ON THE SLIP: the fourball buys in together; four swings on one designated hole;
B25: any ace pays the group. Mechanically each swing is one entry above — nothing changes for the insurer.
B27: NOT BOUND: submitted structure. No revised policy is bound on these terms as at August 2026.

Sheet Valuation
B2: VALUATION & INVESTOR RETURNS
B3: Milestones struck at a flat 3.0× revenue — the round implies 3.69×, so the rating compresses as the company scales. Returns shown on the full R8m for 15%; unrealised marks, not realised returns.
C5: 2027 | D5: Dec 2029 | E5: 2032
B6: Total revenue (ZAR) | C6: =Annual!C17 | D6: =Annual!E17 | E6: =Annual!H17
B7: EBITDA (ZAR) | C7: =Annual!C27 | D7: =Annual!E27 | E7: =Annual!H27
B8: Revenue multiple applied | C8: =C10/C6 | D8: =Assumptions!$C$48 | E8: =Assumptions!$C$48
B9: (2027 shows what the round implies — not an input)
B10: Valuation milestone (ZAR) | C10: =Assumptions!$C$9 | D10: =D6*D8 | E10: =E6*E8
B12: INVESTOR
B13: Ticket (ZAR) | C13: 8000000
B14: Stake (raise / post) | C14: =C13/Assumptions!$C$9
B15: Value of stake | C15: =$C$14*C10 | D15: =$C$14*D10 | E15: =$C$14*E10
B16: Multiple on ticket | C16: =C15/$C$13 | D16: =D15/$C$13 | E16: =E15/$C$13
B17: IRR to Dec 2029 (3 years from Jan 2027) | D17: =D16^(1/3)-1
B18: Unrealised mark on a private holding, not a realised return.
B20: FUNDING
B21: Peak cumulative drawdown (ZAR) | C21: =MIN(Annual!C32:H32)
B22: Raise (ZAR) | C22: =Assumptions!$C$7
B24: MULTIPLE SENSITIVITY — 3.0x is a choice | G24: Headline figures from the pitch: R53.3m / R185.0m (Dec 2029) / R967.8m (2032).
B25: At 2.5x | C25: =Annual!E17*2.5 | D25: =C25*$C$14/$C$13
B26: At 3.0x(used) | C26: =Annual!E17*3.0 | D26: =C26*$C$14/$C$13
B27: At 3.5x | C27: =Annual!E17*3.5 | D27: =C27*$C$14/$C$13
B29: RISKS TO THESE NUMBERS
B30: Jackpot attach (35%) is the decisive assumption — measured by the 90-day pilot before the app ships.
B31: Santam's written sign-off on the peer-game wrapper is a gating milestone, not yet in hand.
B32: The P2P legal opinion is commissioned before launch; the peer layer is free and custody-free by design.
B33: Simulator operator agreements are not signed; no approach made as at Aug 2026.
B34: Peer GMV is an engagement KPI. Get Lucky's revenue from peer stakes is ZERO, permanently.
