Workbook

Sheet Read Me
B2: GET LUCKY GOLF × ERNIE ELS
B3: Valuation bridge — how a 5% founding stake gets to the exit vision
B6: WHAT THIS MODEL DOES
B7: This workbook reverse-engineers the headline valuations in the Ernie pitch (R40m today → R96.8m in 2028 → R500m exit; model shown in $ at FX 18.5).
B8: It shows the subscriber growth, recurring revenue, margin and exit-multiple assumptions that have to hold for those
B9: numbers to be real — so the curve looks earned, not asserted. Every figure you can change is colour-coded.
B11: HOW TO READ THE COLOURS (standard financial-model convention)
B12: BLUE text = an input / assumption you can change. These drive everything else.
B13: BLACK text = a formula. Do not type over these; they recalculate.
B14: GREEN text = a figure pulled from another tab in this workbook.
B15: Yellow shading = a key assumption that is based on histroric average.
B17: THE FOUR TABS
... B21: 4. Ernie's Stake — what 5% is worth at each milestone.

Sheet Assumptions
B2: ASSUMPTIONS
B3: Blue = change me. Yellow = confirm Black = calculated.
B5: DEAL TERMS
B6: Ernie founding equity stake | C6: 0.05 | D6: 5% for name & story, no cash
B7: Post-money valuation today ($) | C7: =40000000/Assumptions!$C$10 -> 2162162.2 | D7: Today's valuation floor (pitch R40m)
B8: Subscription price (USD / month) | C8: 10 | D8: $10/mo unlocks the challenge
B9: Hole-in-one prize (USD) | C9: 10000 | D9: insured payout per verified ace
B10: ZAR per USD | C10: 18.5 | D10: FX assumption — confirm rate to use
B12: OPERATING TODAY
B13: Paying subscribers at month 0 | C13: 2000 | D13: Current subscribers
B14: Monthly subscriber growth — Year 1 | C14: 0.105 | D14: The Ernie affect
B15: Monthly subscriber growth — Year 2 | C15: 0.08 | D15: Tapers as base grows; SA + first intl
B16: Monthly subscriber growth — Year 3 | C16: 0.07 | D16: Global markets open (UK/US/ME/Asia)
B17: Monthly churn rate | C17: 0.04 | D17: % of base lost per month
B18: CAC ($/sub) | C18: 12 | D18: $/sub acquisition target (pitch R225)
B20: ECONOMICS
B21: Gross margin | C21: 0.66 | D21: 66% to Get Lucky
B22: On-course marketing (% of revenue) | C22: 0.1 | D22: 10% on-course marketing
B23: Insured prize risk (% of revenue) | C23: 0.24 | D23: 24% premium for full (100%) cover
B24: Per-round ace probability | C24: 8e-05 | D24: ≈1/12,500 per attempt (amateur odds)
B25: Base operating cost / month today ($) | C25: =350000/Assumptions!$C$10 -> 18918.919 | D25: Today's monthly opex base (pitch R350k/mo)
B26: Ops scaling vs subscribers (0=flat, 1=linear) | C26: 0.65 | D26: 0.65 ≈ service-inclusive SaaS economies of scale
B27: VALUATION
B28: Valuation multiple — ARR (today) | C28: 0 | D28: Solved below to hit $2.16m floor
B29: Valuation multiple — ARR (2028 target) | C29: 2.7 | D29: SaaS-style ARR multiple, pre-scale
B30: Valuation multiple — ARR (2032 exit) | C30: 6 | D30: Rated as global & profitable
B31: Pitch valuation 2028 ($) | C31: =96800000/Assumptions!$C$10 -> 5232432.4 | D31: Pitch milestone — 3-yr plan (R96.8m)
B32: Pitch valuation 2032 ($) | C32: =500000000/Assumptions!$C$10 -> 27027027 | D32: Pitch exit vision (R500m)
B33: SPONSORSHIP & EXIT TRAJECTORY
B34: Sponsorship revenue today ($/yr) | C34: =3000000/Assumptions!$C$10 -> 162162.16 | D34: Pitch baseline (R3m/yr)
B35: Long-term subscriber growth (Y4–Y7, monthly) | C35: 0.018 | D35: To land 2032 model on $27m exit vision
B36: Rounds per subscriber per month | C36: 4 | D36: On-course attempts at the ace

Sheet Build (Monthly)
B2: 36-MONTH BUILD
B3: Subscriber & recurring-revenue build. Growth rate steps by year (see Assumptions).
B5: Month | C5: 1 | D5: 2 | E5: 3 | F5: 4 | G5: 5 | H5: 6 | I5: 7 | J5: 8 | K5: 9 | L5: 10 | M5: 11 | N5: 12 | O5: 13 | P5: 14 | Q5: 15 | R5: 16 | S5: 17 | T5: 18 | U5: 19 | V5: 20 | W5: 21 | X5: 22 | Y5: 23 | Z5: 24 | AA5: 25 | AB5: 26 | AC5: 27 | AD5: 28 | AE5: 29 | AF5: 30 | AG5: 31 | AH5: 32 | AI5: 33 | AJ5: 34 | AK5: 35 | AL5: 36
B6: Opening subscribers | C6: =Assumptions!$C$13 -> 2000 | D6: =C10 -> 2130 | E6: =D10 -> 2268.45 | F6: =E10 -> 2415.8993 | G6: =F10 -> 2572.9327 | H6: =G10 -> 2740.1733 | I6: =H10 -> 2918.2846 | J6: =I10 -> 3107.9731 | K6: =J10 -> 3309.9913 | ... AL6: =AK10 -> 9437.0191
B7: Net growth rate (mo) | C7: =Assumptions!$C$14 -> 0.105 | D7: =Assumptions!$C$14 -> 0.105 | E7: =Assumptions!$C$14 -> 0.105 | F7: =Assumptions!$C$14 -> 0.105 | G7: =Assumptions!$C$14 -> 0.105 | H7: =Assumptions!$C$14 -> 0.105 | I7: =Assumptions!$C$14 -> 0.105 | J7: =Assumptions!$C$14 -> 0.105 | ... N7: =Assumptions!$C$14 -> 0.105 | O7: =Assumptions!$C$15 -> 0.08 | P7: =Assumptions!$C$15 -> 0.08 | Q7: =Assumptions!$C$15 -> 0.08 | R7: =Assumptions!$C$15 -> 0.08 | S7: =Assumptions!$C$15 -> 0.08 | T7: =Assumptions!$C$15 -> 0.08 | U7: =Assumptions!$C$15 -> 0.08 | V7: =Assumptions!$C$15 -> 0.08 | ... Z7: =Assumptions!$C$15 -> 0.08 | AA7: =Assumptions!$C$16 -> 0.07 | AB7: =Assumptions!$C$16 -> 0.07 | AC7: =Assumptions!$C$16 -> 0.07 | AD7: =Assumptions!$C$16 -> 0.07 | AE7: =Assumptions!$C$16 -> 0.07 | AF7: =Assumptions!$C$16 -> 0.07 | AG7: =Assumptions!$C$16 -> 0.07 | AH7: =Assumptions!$C$16 -> 0.07 | ... AL7: =Assumptions!$C$16 -> 0.07
B8: Gross adds + retained | C8: =C6*(1+C7) -> 2210 | D8: =D6*(1+D7) -> 2353.65 | E8: =E6*(1+E7) -> 2506.6373 | F8: =F6*(1+F7) -> 2669.5687 | G8: =G6*(1+G7) -> 2843.0906 | H8: =H6*(1+H7) -> 3027.8915 | I8: =I6*(1+I7) -> 3224.7045 | J8: =J6*(1+J7) -> 3434.3103 | ... AL8: =AL6*(1+AL7) -> 10097.61
B9: Churned | C9: =-C6*Assumptions!$C$17 -> -80 | D9: =-D6*Assumptions!$C$17 -> -85.2 | E9: =-E6*Assumptions!$C$17 -> -90.738 | F9: =-F6*Assumptions!$C$17 -> -96.63597 | G9: =-G6*Assumptions!$C$17 -> -102.91731 | H9: =-H6*Assumptions!$C$17 -> -109.60693 | I9: =-I6*Assumptions!$C$17 -> -116.73138 | J9: =-J6*Assumptions!$C$17 -> -124.31892 | ... AL9: =-AL6*Assumptions!$C$17 -> -377.48076
B10: Closing subscribers | C10: =C8+C9 -> 2130 | D10: =D8+D9 -> 2268.45 | E10: =E8+E9 -> 2415.8993 | F10: =F8+F9 -> 2572.9327 | G10: =G8+G9 -> 2740.1733 | H10: =H8+H9 -> 2918.2846 | I10: =I8+I9 -> 3107.9731 | J10: =J8+J9 -> 3309.9913 | ... AL10: =AL8+AL9 -> 9720.1296
B11: MRR ($) | C11: =C10*Assumptions!$C$8 -> 21300 | D11: =D10*Assumptions!$C$8 -> 22684.5 | E11: =E10*Assumptions!$C$8 -> 24158.993 | F11: =F10*Assumptions!$C$8 -> 25729.327 | G11: =G10*Assumptions!$C$8 -> 27401.733 | H11: =H10*Assumptions!$C$8 -> 29182.846 | I11: =I10*Assumptions!$C$8 -> 31079.731 | J11: =J10*Assumptions!$C$8 -> 33099.913 | ... AL11: =AL10*Assumptions!$C$8 -> 97201.296
B12: Marketing spend ($) | C12: =C11*Assumptions!$C$22 -> 2130 | D12: =D11*Assumptions!$C$22 -> 2268.45 | E12: =E11*Assumptions!$C$22 -> 2415.8993 | F12: =F11*Assumptions!$C$22 -> 2572.9327 | G12: =G11*Assumptions!$C$22 -> 2740.1733 | H12: =H11*Assumptions!$C$22 -> 2918.2846 | I12: =I11*Assumptions!$C$22 -> 3107.9731 | J12: =J11*Assumptions!$C$22 -> 3309.9913 | ... AL12: =AL11*Assumptions!$C$22 -> 9720.1296
B13: Prize payouts ($) | C13: =Assumptions!$C$9*(INT(SUM($B$10:C10)*Assumptions!$C$36*Assumptions!$C$24)-INT(SUM($B$10:B10)*Assumptions!$C$36*Assumptions!$C$24)) -> 0 | D13: =Assumptions!$C$9*(INT(SUM($B$10:D10)*Assumptions!$C$36*Assumptions!$C$24)-INT(SUM($B$10:C10)*Assumptions!$C$36*Assumptions!$C$24)) -> 10000 | E13: =Assumptions!$C$9*(INT(SUM($B$10:E10)*Assumptions!$C$36*Assumptions!$C$24)-INT(SUM($B$10:D10)*Assumptions!$C$36*Assumptions!$C$24)) -> 10000 | F13: =Assumptions!$C$9*(INT(SUM($B$10:F10)*Assumptions!$C$36*Assumptions!$C$24)-INT(SUM($B$10:E10)*Assumptions!$C$36*Assumptions!$C$24)) -> 10000 | G13: =Assumptions!$C$9*(INT(SUM($B$10:G10)*Assumptions!$C$36*Assumptions!$C$24)-INT(SUM($B$10:F10)*Assumptions!$C$36*Assumptions!$C$24)) -> 0 | H13: =Assumptions!$C$9*(INT(SUM($B$10:H10)*Assumptions!$C$36*Assumptions!$C$24)-INT(SUM($B$10:G10)*Assumptions!$C$36*Assumptions!$C$24)) -> 10000 | I13: =Assumptions!$C$9*(INT(SUM($B$10:I10)*Assumptions!$C$36*Assumptions!$C$24)-INT(SUM($B$10:H10)*Assumptions!$C$36*Assumptions!$C$24)) -> 10000 | J13: =Assumptions!$C$9*(INT(SUM($B$10:J10)*Assumptions!$C$36*Assumptions!$C$24)-INT(SUM($B$10:I10)*Assumptions!$C$36*Assumptions!$C$24)) -> 10000 | ... AL13: =Assumptions!$C$9*(INT(SUM($B$10:AL10)*Assumptions!$C$36*Assumptions!$C$24)-INT(SUM($B$10:AK10)*Assumptions!$C$36*Assumptions!$C$24)) -> 40000
B14: Sponsorship ($) | C14: =Assumptions!$C$34/12*C10/$C$10 -> 13513.514 | D14: =Assumptions!$C$34/12*D10/$C$10 -> 14391.892 | E14: =Assumptions!$C$34/12*E10/$C$10 -> 15327.365 | F14: =Assumptions!$C$34/12*F10/$C$10 -> 16323.644 | G14: =Assumptions!$C$34/12*G10/$C$10 -> 17384.68 | H14: =Assumptions!$C$34/12*H10/$C$10 -> 18514.685 | I14: =Assumptions!$C$34/12*I10/$C$10 -> 19718.139 | J14: =Assumptions!$C$34/12*J10/$C$10 -> 20999.818 | ... AL14: =Assumptions!$C$34/12*AL10/$C$10 -> 61668.124

Sheet Valuation
B2: VALUATION BRIDGE
B3: Annual roll-up of the monthly build, then the valuation walk to the pitch milestones.
B5: Metric | C5: 2026 | D5: 2029 (Yr3 plan) | E5: 2032 (Exit vision)
B6: Subscribers/ Entries | C6: ='Build (Monthly)'!C10 -> 2130 | D6: ='Build (Monthly)'!AL10 -> 9720.1296 | E6: ='Build (Monthly)'!AL10*(1+Assumptions!$C$35)^48 -> 22885.763 | G6: 2032 extends the Yr3 exit ramp
B7: Subscription ARR ($) | C7: =SUM('Build (Monthly)'!C11:N11) -> 369996.15 | D7: ='Build (Monthly)'!AL11*12 -> 1166415.6 | E7: =E6*Assumptions!$C$8*12 -> 2746291.6 | G7: Sum of MRR across months 1–12 (actual 2026 revenue)
B8: Sponsorship revenue ($) | C8: =SUM('Build (Monthly)'!C14:N14) -> 234739.34 | D8: ='Build (Monthly)'!AL14*12 -> 740017.48 | E8: =Assumptions!$C$34*E6/$C$6 -> 1742349.7 | G8: Sum of monthly sponsorship across 2026
B9: Total annual revenue ($) | C9: =C7+C8 -> 604735.5 | D9: =D7+D8 -> 1906433 | E9: =E7+E8 -> 4488641.3 | G9: Subscriptions + sponsorship — drives valuation
B10: Gross profit ($) | C10: =C9*Assumptions!$C$21 -> 399125.43 | D10: =D9*Assumptions!$C$21 -> 1258245.8 | E10: =E9*Assumptions!$C$21 -> 2962503.2 | G10: Pitch gross margin 78%
B11: EBITDA proxy ($) | C11: =C10-Assumptions!$C$25*12*(C6/$C$6)^Assumptions!$C$26-C9*Assumptions!$C$23 -> 26961.881 | D11: =D10-Assumptions!$C$25*12*(D6/$C$6)^Assumptions!$C$26-D9*Assumptions!$C$23 -> 191701.37 | E11: =E10-Assumptions!$C$25*12*(E6/$C$6)^Assumptions!$C$26-E9*Assumptions!$C$23 -> 822681.9 | G11: GP less scaled opex less insurance premium (24% of revenue, 100% cover). Prize payouts excluded — covered by insurer.
B13: VALUATION WALK
B14: Implied revenue multiple | C14: =Assumptions!$C$7/C9 -> 3.5753849 | D14: =Assumptions!$C$29 -> 2.7 | E14: =Assumptions!$C$30 -> 6 | G14: Today solved to the $2.16m floor; out-years from Assumptions
B15: Valuation milestone — pitch ($) | C15: =Assumptions!$C$7 -> 2162162.2 | D15: =Assumptions!$C$31 -> 5232432.4 | E15: =Assumptions!$C$32 -> 27027027 | G15: Headline figures from the pitch
B16: Valuation — model-implied ($) | C16: =C9*C14 -> 2162162.2 | D16: =D9*D14 -> 5147369.2 | E16: =E9*E14 -> 26931848 | G16: Sanity check: does the ramp + multiple reach the milestone?
B17: Gap (model vs pitch) ($)
B19: Memo — model valuation in ZAR | C19: =C16*Assumptions!$C$10 -> 40000000 | D19: =D16*Assumptions!$C$10 -> 95226330 | E19: =E16*Assumptions!$C$10 -> 4.9823918e+08
B20: Memo — pitch milestone in ZAR | C20: =Assumptions!$C$7*Assumptions!$C$10 -> 40000000 | D20: =Assumptions!$C$31*Assumptions!$C$10 -> 96800000 | E20: =Assumptions!$C$32*Assumptions!$C$10 -> 500000000
B22: WHY 6× REVENUE AT EXIT (2032)
B23: Engaged subscriber database | C23: Recurring golfers opted into a high-intent niche product are the core asset — a clean, targetable distribution channel for golf brands, media partners and sponsors. The valuation reflects the database itself, not just the topline.
B24: Strategic partner optionality | C24: At scale, the platform unlocks multiple exit paths: license access to a golf brand (Callaway/TaylorMade), co-brand prize pools with a tour or media rights holder, integrate with a sportsbook, or sell outright to a sports-tech acquirer. Optionality justifies a strategic premium over pure SaaS multiples.
B25: Comparable engaged communities | C25: Engaged-community subscription businesses (Strava, Peloton, Whoop) have transacted in the 5–10× revenue range at similar scale. 6× sits mid-band — conservative for a niche category leader with strategic upside.
B26: Risk to the multiple | C26: If sub growth stalls or the engaged-community thesis weakens, the multiple compresses toward pure SaaS (3–4×), which would land 2032 closer to $13–18m (R250–335m) rather than $27m (R500m).

Sheet Ernie's Stake
B2: ERNIE'S 5%
B3: No cash in. Name & story for 5%. Here's what that 5% rides to.
C5: Today | D5: 2028 (3-yr plan) | E5: 2032 (Exit vision)
B6: Company valuation ($) | C6: =Valuation!C15 -> 2162162.2 | D6: =Valuation!D15 -> 5232432.4 | E6: =Valuation!E15 -> 27027027 | F6: From Valuation tab (pitch milestones)
B7: Ernie's stake % | C7: =Assumptions!$C$6 -> 0.05 | D7: =Assumptions!$C$6 -> 0.05 | E7: =Assumptions!$C$6 -> 0.05 | F7: Non Dilutive
B8: Ernie's equity value ($) | C8: =C6*C7 -> 108108.11 | D8: =D6*D7 -> 261621.62 | E8: =E6*E7 -> 1351351.4 | F8: What the 5% is worth at each milestone
B10: Value created for Ernie vs today ($) | C10: =C8-C8 -> 0 | D10: =D8-C8 -> 153513.51 | E10: =E8-C8 -> 1243243.2 | F10: Upside on a zero-cash, zero-time stake
B11: Multiple on entry value | C11: =C8/C8 -> 1 | D11: =D8/C8 -> 2.42 | E11: =E8/C8 -> 12.5 | F11: Multiple on entry. CAGR: ~34% to 2028 (3 yrs) / ~43% to 2032 (7 yrs)
B12: Memo — Ernie's stake in ZAR | C12: =C8*Assumptions!$C$10 -> 2000000 | D12: =D8*Assumptions!$C$10 -> 4840000 | E12: =E8*Assumptions!$C$10 -> 25000000
B13: Figures reflect the company's stated valuation milestones from the 2025 raise and 3-year plan. They illustrate the trajectory a 5% holding moves with — not a guarantee of return. Current operating inputs are illustrative until replaced with live traction.
